{
  "metadata": {
    "generated_at": "2026-03-22T04:15:49Z",
    "source": "repology-dump",
    "distro": "t2",
    "total_mappings": 1991
  },
  "mappings": {
    "0install": "zero-install",
    "7zip": "sevenzip",
    "a2ps": "a2ps",
    "a52dec": "a52dec",
    "aalib": "aalib",
    "abcde": "abcde",
    "abduco": "abduco",
    "abi-compliance-checker": "abi-compliance-checker",
    "abseil-cpp": "abseil",
    "ace": "ace",
    "ack": "ack",
    "acl": "acl",
    "acme": "certbot",
    "acpica": "acpica",
    "ada-url": "ada-url",
    "admesh": "admesh",
    "adwaita-icon-theme": "adwaita-icon-theme",
    "aerc": "aerc",
    "afio": "afio",
    "agg": "libagg",
    "aha": "aha",
    "aichat": "aichat",
    "aide": "aide",
    "aircrack-ng": "aircrack-ng",
    "allegro": "allegro",
    "alpine": "alpine",
    "alsa-lib": "alsa-lib",
    "ansible": "ansible",
    "antiword": "antiword",
    "aoeui": "aoeui",
    "apache": "httpd",
    "apache-ant": "ant",
    "apcupsd": "apcupsd",
    "apenwarr-redo": "redo",
    "appstream": "appstream",
    "appstream-glib": "appstream-glib",
    "apr": "apr",
    "apr-util": "apr-util",
    "aqbanking": "aqbanking",
    "argon2": "argon2",
    "argus": "argus-clients",
    "argyllcms": "argyll-cms",
    "aria2": "aria2",
    "armadillo": "armadillo",
    "arping": "arping",
    "asc": "asc",
    "asciidoc": "asciidoc",
    "asciidoctor": "asciidoctor",
    "asciinema": "asciinema",
    "asio": "asio",
    "asn1c": "asn1c",
    "aspell": "aspell",
    "assimp": "assimp",
    "astyle": "astyle",
    "asymptote": "asymptote",
    "at-spi2-core": "at-spi2-core",
    "atf": "atf",
    "atkmm": "atkmm",
    "atkmm1": "atkmm",
    "atomicparsley": "atomicparsley",
    "atop": "atop",
    "attr": "attr",
    "atuin": "atuin",
    "aubio": "aubio",
    "audacious": "audacious",
    "augeas": "augeas",
    "autoconf": "autoconf",
    "autoconf-2.13": "autoconf",
    "autoconf-archive": "autoconf-archive",
    "autogen": "autogen",
    "autojump": "autojump",
    "automake": "automake",
    "autotrace": "autotrace",
    "avahi": "avahi",
    "avfs": "avfs",
    "avrdude": "avrdude",
    "axel": "axel",
    "b3sum": "b3sum",
    "b43-fwcutter": "b43-fwcutter",
    "babeld": "babeld",
    "babl": "babl",
    "bacula": "bacula-fd",
    "bandwhich": "bandwhich",
    "baobab": "baobab",
    "barcode": "gnu-barcode",
    "bash": "bash",
    "bash-completion": "bash-completion",
    "bat": "bat",
    "bbe": "bbe",
    "bc": "bc",
    "bchunk": "bchunk",
    "bcpp": "bcpp",
    "bcrypt": "bcrypt",
    "bdb": "berkeley-db",
    "bdb-java": "berkeley-db",
    "bdb33": "berkeley-db",
    "bdb33-java": "berkeley-db",
    "bdftopcf": "bdftopcf",
    "beanstalkd": "beanstalkd",
    "beecrypt": "beecrypt",
    "benchmark": "google-benchmark",
    "binaryen": "binaryen",
    "bind": "bind",
    "binutils": "aarch64-elf-binutils",
    "binwalk": "binwalk",
    "bison": "bison",
    "bitlbee": "bitlbee",
    "bitwise": "bitwise",
    "blink": "blink",
    "blisp": "blisp",
    "blitz": "blitz",
    "bloaty": "bloaty",
    "blosc": "c-blosc",
    "blueprint-compiler": "blueprint-compiler",
    "bluez": "bluez",
    "bmon": "bmon",
    "bochs": "bochs",
    "boehm-gc": "bdw-gc",
    "bogofilter": "bogofilter",
    "bolt": "clang-format",
    "bombadillo": "bombadillo",
    "bonnie++": "bonnie++",
    "boost": "boost",
    "bootterm": "bootterm",
    "borgmatic": "borgmatic",
    "botan": "botan",
    "bpytop": "bpytop",
    "brotli": "brotli",
    "bsdiff": "bsdiff",
    "btop": "btop",
    "btpd": "btpd",
    "btrfs-progs": "btrfs-progs",
    "bubblewrap": "bubblewrap",
    "buildkit": "buildkit",
    "buku": "buku",
    "bullet": "bullet",
    "bvi": "bvi",
    "bwm-ng": "bwm-ng",
    "byobu": "byobu",
    "bzip2": "bzip2",
    "bzip3": "bzip3",
    "c-ares": "c-ares",
    "c3c": "c3c",
    "ca-certificates": "ca-certificates",
    "cabal-install": "cabal-install",
    "cabextract": "cabextract",
    "cadaver": "cadaver",
    "cairo": "cairo",
    "cairomm": "cairomm",
    "cairomm1": "cairomm",
    "capstone": "capstone",
    "cargo-c": "cargo-c",
    "cariddi": "cariddi",
    "carla": "carla",
    "cassandra-cpp-driver": "cassandra-cpp-driver",
    "catch2": "catch2",
    "catimg": "catimg",
    "cava": "cava",
    "cbindgen": "cbindgen",
    "cbonsai": "cbonsai",
    "ccache": "ccache",
    "ccd2iso": "ccd2iso",
    "ccls": "ccls",
    "cd-discid": "cd-discid",
    "cdlabelgen": "cdlabelgen",
    "cdrdao": "cdrdao",
    "cdrtools": "cdrtools",
    "cereal": "cereal",
    "ceres-solver": "ceres-solver",
    "certbot": "certbot",
    "cf": "cf",
    "cfengine": "cfengine",
    "cflow": "cflow",
    "cgal": "cgal",
    "cgdb": "cgdb",
    "cgif": "cgif",
    "cgit": "cgit",
    "cglm": "cglm",
    "cgoban": "cgoban",
    "chafa": "chafa",
    "chardet": "chardet",
    "charls": "charls",
    "check": "check",
    "check_postgres": "check_postgres",
    "chez-scheme": "chezscheme",
    "chibi-scheme": "chibi-scheme",
    "chkrootkit": "chkrootkit",
    "chmlib": "chmlib",
    "chromaprint": "chromaprint",
    "chrony": "chrony",
    "chrpath": "chrpath",
    "cjson": "cjson",
    "ck": "concurrencykit",
    "clamav": "clamav",
    "clang": "clang-format",
    "claws-mail": "claws-mail",
    "cli11": "cli11",
    "clifm": "clifm",
    "clinfo": "clinfo",
    "cling": "cling",
    "clingo": "clingo",
    "clisp": "clisp",
    "cln": "cln",
    "cloc": "cloc",
    "cloudflared": "cloudflared",
    "cmake": "cmake",
    "cmark": "cmark",
    "cmatrix": "cmatrix",
    "cmocka": "cmocka",
    "cntlm": "cntlm",
    "coin": "coin3d",
    "collectd": "collectd",
    "compiler-rt": "clang-format",
    "conmon": "conmon",
    "console_bridge": "console_bridge",
    "containerd": "containerd",
    "coreutils": "coreutils",
    "corkscrew": "corkscrew",
    "coturn": "coturn",
    "couchdb": "couchdb",
    "cowsay": "cowsay",
    "cpio": "cpio",
    "cppcheck": "cppcheck",
    "cpptest": "cpptest",
    "cppunit": "cppunit",
    "cpputest": "cpputest",
    "cpufeatures": "cpu_features",
    "cpufetch": "cpufetch",
    "cracklib": "cracklib",
    "crm114": "crm114",
    "croc": "croc",
    "crossplane": "crossplane",
    "crypto++": "cryptopp",
    "cscope": "cscope",
    "csmith": "csmith",
    "ctags": "universal-ctags",
    "cunit": "cunit",
    "cups": "cups",
    "curl": "curl",
    "curlftpfs": "curlftpfs",
    "curlpp": "curlpp",
    "cvs": "cvs",
    "cxxopts": "cxxopts",
    "cxxtest": "cxxtest",
    "cyme": "cyme",
    "cyrus-sasl": "cyrus-sasl",
    "cyrus-sasl2": "cyrus-sasl",
    "cython": "cython",
    "d2": "d2",
    "daemon": "daemon",
    "dante": "dante",
    "dart": "dart-sdk",
    "dash": "dash-shell",
    "datamash": "datamash",
    "date": "howard-hinnant-date",
    "dateutils": "dateutils",
    "dav1d": "dav1d",
    "dbus": "dbus",
    "dbus-glib": "dbus-glib",
    "dcadec": "dcadec",
    "dcmtk": "dcmtk",
    "dcraw": "dcraw",
    "ddate": "ddate",
    "ddclient": "ddclient",
    "ddd": "ddd",
    "ddgr": "ddgr",
    "ddrescue": "ddrescue",
    "dejagnu": "deja-gnu",
    "delta": "git-delta",
    "delve": "delve",
    "desktop-file-utils": "desktop-file-utils",
    "devil": "devil",
    "dfu-programmer": "dfu-programmer",
    "dfu-util": "dfu-util",
    "dhcping": "dhcping",
    "dialog": "dialog",
    "dictd": "dict",
    "dictd_client": "dict",
    "diction": "diction",
    "diffoscope": "diffoscope",
    "diffstat": "diffstat",
    "difftastic": "difftastic",
    "diffutils": "diffutils",
    "dillo": "dillo",
    "directx-headers": "directx-headers",
    "discount": "discount",
    "disktype": "disktype",
    "distcc": "distcc",
    "djbdns": "djbdns",
    "djvulibre": "djvulibre",
    "dlpack": "dlpack",
    "dmalloc": "dmalloc",
    "dmenu": "dmenu",
    "dmg2img": "dmg2img",
    "dnsmasq": "dnsmasq",
    "dnsperf": "dnsperf",
    "dnstop": "dnstop",
    "dnstracer": "dnstracer",
    "dnstwist": "dnstwist",
    "docbook-xsl": "docbook-xsl",
    "docbook2x": "docbook2x",
    "docker-buildx": "docker-buildx",
    "docker-compose": "docker-compose",
    "docker-engine": "docker-engine",
    "doctest": "doctest",
    "doctl": "doctl",
    "docutils": "docutils",
    "dos2unix": "dos2unix",
    "dosfstools": "dosfstools",
    "double-conversion": "double-conversion",
    "dovecot": "dovecot",
    "doxygen": "doxygen",
    "dpkg": "dpkg",
    "dqlite": "dqlite",
    "dragonbox": "dragonbox",
    "dropbear": "dropbear",
    "dtc": "dtc",
    "dua-cli": "dua-cli",
    "duf": "duf",
    "duktape": "duktape",
    "dune": "dune",
    "duplicity": "duplicity",
    "durdraw": "durdraw",
    "dust": "dust",
    "dvd+rwtools": "dvd+rw-tools",
    "dvdauthor": "dvdauthor",
    "dvdbackup": "dvdbackup",
    "dwdiff": "dwdiff",
    "dwm": "dwm",
    "dynamips": "dynamips",
    "dysk": "dysk",
    "e2fsprogs": "e2fsprogs",
    "e2tools": "e2tools",
    "easytag": "easy-tag",
    "eatmemory": "eatmemory",
    "ebook-tools": "ebook-tools",
    "ecasound": "ecasound",
    "ecl": "ecl",
    "ed": "ed",
    "editorconfig": "editorconfig",
    "efl": "efl",
    "eg": "eg",
    "eigen": "eigen",
    "elfio": "elfio",
    "emacs": "emacs",
    "embree": "embree",
    "enca": "enca",
    "enchant": "enchant",
    "enet": "enet",
    "enigma": "enigma",
    "enscript": "enscript",
    "entr": "entr",
    "epeg": "epeg",
    "epic5": "epic5",
    "epr": "epr",
    "erlang-otp": "erlang",
    "espeak": "espeak",
    "ettercap": "ettercap",
    "evince": "evince",
    "exact-image": "exact-image",
    "exempi": "exempi",
    "exiftool": "exiftool",
    "exim": "exim",
    "exiv2": "exiv2",
    "expat": "expat",
    "expect": "expect",
    "extra-cmake-modules": "extra-cmake-modules",
    "eyed3": "eye-d3",
    "eza": "eza",
    "faac": "faac",
    "faad": "faad2",
    "fabric": "fabric",
    "fabricai": "fabric-ai",
    "fail2ban": "fail2ban",
    "fakeroot": "fakeroot",
    "fann": "fann",
    "fast_float": "fast_float",
    "fastcgi": "fcgi",
    "fastfetch": "fastfetch",
    "fastjar": "fastjar",
    "faudio": "faudio",
    "fcft": "fcft",
    "fcgiwrap": "fcgiwrap",
    "fd": "fd",
    "fdupes": "fdupes",
    "feh": "feh",
    "fennel": "fennel",
    "fetchmail": "fetchmail",
    "ffcall": "libffcall",
    "fff": "fff",
    "ffmpeg": "ffmpeg",
    "fftw": "fftw",
    "fftw3": "fftw",
    "fig2dev": "fig2dev",
    "figlet": "figlet",
    "file": "file-formula",
    "file-roller": "file-roller",
    "findutils": "findutils",
    "fio": "fio",
    "fish": "fish",
    "flac": "flac",
    "flang": "clang-format",
    "flashrom": "flashrom",
    "flatbuffers": "flatbuffers",
    "flawfinder": "flawfinder",
    "flex": "flex",
    "flint": "flint",
    "fltk": "fltk",
    "fluidsynth": "fluid-synth",
    "fmt": "fmt",
    "font-util": "font-util",
    "fontconfig": "fontconfig",
    "fontforge": "fontforge",
    "fonttools": "fonttools",
    "foot": "foot",
    "fop": "fop",
    "fossil": "fossil",
    "fox": "fox",
    "fpc": "fpc",
    "fping": "fping",
    "fprobe": "fprobe",
    "fragroute": "fragroute",
    "freealut": "freealut",
    "freeciv": "freeciv",
    "freeglut": "freeglut",
    "freeimage": "freeimage",
    "freeipmi": "freeipmi",
    "freeradius": "freeradius-server",
    "freerdp": "freerdp",
    "freetds": "freetds",
    "freetype": "freetype",
    "freetype1": "freetype",
    "frei0r-plugins": "frei0r",
    "fresh-editor": "fresh-editor",
    "fribidi": "fribidi",
    "frotz": "frotz",
    "fs-uae": "fs-uae",
    "fstrm": "fstrm",
    "ftgl": "ftgl",
    "fuse": "libfuse",
    "fuse2": "libfuse",
    "fwupd": "fwupd",
    "fzf": "fzf",
    "gallery-dl": "gallery-dl",
    "gammu": "gammu",
    "gawk": "gawk",
    "gcab": "gcab",
    "gcc": "aarch64-elf-gcc",
    "gcl": "gcl",
    "gcr": "gcr",
    "gcr3": "gcr",
    "gdal": "gdal",
    "gdb": "aarch64-elf-gdb",
    "gdbm": "gdbm",
    "gdk-pixbuf": "gdk-pixbuf",
    "gdk-pixbuf10": "gdk-pixbuf",
    "gdl": "gdl",
    "gedit": "gedit",
    "geeqie": "geeqie",
    "gegl": "gegl",
    "genext2fs": "genext2fs",
    "gengetopt": "gengetopt",
    "gensio": "gensio",
    "geocode-glib": "geocode-glib",
    "geos": "geos",
    "getmail": "getmail6",
    "gettext": "gettext",
    "gexiv2": "gexiv2",
    "gflags": "gflags",
    "ggml": "ggml",
    "ghc": "ghc",
    "ghex": "ghex",
    "ghidra": "ghidra",
    "ghostscript": "ghostscript",
    "gi-docgen": "gi-docgen",
    "gifsicle": "gifsicle",
    "ginac": "ginac",
    "git": "git",
    "git-cola": "git-cola",
    "git-lfs": "git-lfs",
    "git-machete": "git-machete",
    "git-secret": "git-secret",
    "git-who": "git-who",
    "github-cli": "gh",
    "github-mcp-server": "github-mcp-server",
    "gitleaks": "gitleaks",
    "gitlogue": "gitlogue",
    "gjs": "gjs",
    "gkrellm": "gkrellm",
    "glade": "glade",
    "glade10": "glade",
    "glade3": "glade",
    "glances": "glances",
    "glaze": "glaze",
    "glew": "glew",
    "glfw": "glfw",
    "glib": "glib",
    "glib-networking": "glib-networking",
    "glib12": "glib",
    "glibc": "glibc",
    "glibc32": "glibc",
    "glibmm": "glibmm",
    "glibmm2": "glibmm",
    "glm": "glm",
    "glog": "glog",
    "gloox": "gloox",
    "glow": "glow",
    "glpk": "glpk",
    "glslang": "glslang",
    "glu": "mesa-glu",
    "gmime": "gmime",
    "gmp": "gmp",
    "gnome-autoar": "gnome-autoar",
    "gnome-builder": "gnome-builder",
    "gnome-online-accounts": "gnome-online-accounts",
    "gnuchess": "gnu-chess",
    "gnucobol": "gnucobol",
    "gnugo": "gnu-go",
    "gnugts": "gts",
    "gnumeric": "gnumeric",
    "gnunet": "gnunet",
    "gnupg": "gnupg",
    "gnupg2": "gnupg",
    "gnuplot": "gnuplot",
    "gnustep-base": "gnustep-base",
    "gnustep-make": "gnustep-make",
    "gnutls": "gnutls",
    "go": "go",
    "go-md2man": "go-md2man",
    "go-task": "go-task",
    "goaccess": "goaccess",
    "goawk": "goawk",
    "gobject-introspection": "gobject-introspection",
    "gocr": "gocr",
    "goffice": "goffice",
    "golangci-lint-langserver": "golangci-lint-langserver",
    "gom": "gom",
    "goocanvas": "goocanvas",
    "gopls": "gopls",
    "govc": "govc",
    "gpa": "gpa",
    "gpac": "gpac",
    "gperf": "gperf",
    "gpgme": "gpgme",
    "gpgmepp": "gpgmepp",
    "gpgmepy": "gpgmepy",
    "gphoto": "gphoto2",
    "gpsd": "gpsd",
    "gptfdisk": "gptfdisk",
    "gputils": "gputils",
    "grace": "grace",
    "gradle": "gradle",
    "grafana": "grafana",
    "graphene": "graphene",
    "graphicsmagick": "graphicsmagick",
    "graphite2": "graphite2",
    "graphviz": "graphviz",
    "grep": "grep",
    "groff": "groff",
    "gsasl": "gsasl",
    "gsettings-desktop-schemas": "gsettings-desktop-schemas",
    "gsl": "gsl",
    "gsm": "libgsm",
    "gsoap": "gsoap",
    "gspell": "gspell",
    "gssdp": "gssdp",
    "gstreamer": "gstreamer",
    "gtest": "googletest",
    "gtk": "gtk+",
    "gtk+": "gtk+",
    "gtk+12": "gtk+",
    "gtk+2": "gtk+",
    "gtk-doc": "gtk-doc",
    "gtk-vnc": "gtk-vnc",
    "gtkglext": "gtkglext",
    "gtkmm": "gtkmm",
    "gtkmm12": "gtkmm",
    "gtkmm3": "gtkmm",
    "gtksourceview": "gtksourceview3",
    "gtksourceview4": "gtksourceview3",
    "gtkspell": "gtkspell3",
    "gucharmap": "gucharmap",
    "gudev": "libgudev",
    "guile": "guile",
    "gum": "gum",
    "gumbo-parser": "gumbo-parser",
    "gupnp": "gupnp",
    "gupnp-av": "gupnp-av",
    "gwenhywfar": "gwenhywfar",
    "gzip": "gzip",
    "hamlib": "hamlib",
    "handbrake": "handbrake",
    "haproxy": "haproxy",
    "harfbuzz": "harfbuzz",
    "hashcat": "hashcat",
    "hdf5": "hdf5",
    "hdrhistogram-c": "hdrhistogram_c",
    "headson": "headson",
    "heimdal": "heimdal",
    "helix": "helix",
    "helm": "helm",
    "helmfile": "helmfile",
    "help2man": "help2man",
    "hercules": "hercules",
    "hexedit": "hexedit",
    "hexyl": "hexyl",
    "hfsutils": "hfsutils",
    "hicolor-icon-theme": "hicolor-icon-theme",
    "hidapi": "hidapi",
    "highs": "highs",
    "highway": "highway",
    "hiredis": "hiredis",
    "hivex": "hivex",
    "hte": "ht",
    "htmldoc": "htmldoc",
    "htmlq": "htmlq",
    "htop": "htop",
    "htslib": "htslib",
    "httrack": "httrack",
    "hugo": "hugo",
    "hunspell": "hunspell",
    "hwloc": "hwloc",
    "hydra": "hydra",
    "hyperfine": "hyperfine",
    "hyperscan": "hyperscan",
    "i2c-tools": "i2c-tools",
    "iat": "iat",
    "icecast": "icecast",
    "icecream": "icecream",
    "icon-naming-utils": "icon-naming-utils",
    "icoutils": "icoutils",
    "icu4c": "icu4c@74",
    "id3lib": "id3lib",
    "ideviceinstaller": "ideviceinstaller",
    "ifstat": "ifstat",
    "iftop": "iftop",
    "ifuse": "ifuse",
    "ilmbase": "openexr",
    "imagemagick": "imagemagick",
    "imake": "imake",
    "imlib2": "imlib2",
    "immer": "immer",
    "inadyn": "inadyn",
    "incus": "incus",
    "indent": "gnu-indent",
    "inetutils": "inetutils",
    "inih": "inih",
    "iniparser": "iniparser",
    "inotify-tools": "inotify-tools",
    "intel-isa-l": "isa-l",
    "intltool": "intltool",
    "iodine": "iodine",
    "ioping": "ioping",
    "iperf": "iperf3",
    "ipmiutil": "ipmiutil",
    "ipopt": "ipopt",
    "iproute2": "iproute2",
    "iptables": "iptables",
    "iputils": "iputils",
    "ircii": "ircii",
    "irssi": "irssi",
    "isl": "isl",
    "iso-codes": "iso-codes",
    "ispc": "ispc",
    "isync": "isync",
    "itstool": "itstool",
    "ivykis": "ivykis",
    "jack": "jack",
    "jack2": "jack",
    "janet": "janet",
    "jansson": "jansson",
    "jasper": "jasper",
    "jbig2dec": "jbig2dec",
    "jbig2enc": "jbig2enc",
    "jbigkit": "jbigkit",
    "jed": "jed",
    "jemalloc": "jemalloc",
    "jetty": "jetty",
    "jhead": "jhead",
    "jinja2-cli": "jinja2-cli",
    "jo": "jo",
    "joe": "joe",
    "john": "john",
    "jose": "jose",
    "jpeginfo": "jpeginfo",
    "jpegoptim": "jpegoptim",
    "jq": "jq",
    "jshon": "jshon",
    "json-c": "json-c",
    "json-glib": "json-glib",
    "jsoncpp": "jsoncpp",
    "jsonnet": "jsonnet",
    "jsonrpc-glib": "jsonrpc-glib",
    "jujutsu": "jj",
    "julia": "julia",
    "julius": "julius",
    "just": "just",
    "k9s": "k9s",
    "kakoune": "kakoune",
    "karchive": "karchive",
    "kdoctools": "kdoctools",
    "kea": "kea",
    "keychain": "keychain",
    "keyutils": "keyutils",
    "ki18n": "ki18n",
    "kmod": "kmod",
    "ko": "ko",
    "kops": "kops",
    "kotlin": "kotlin",
    "krb5": "krb5",
    "ksh": "ksh93",
    "ktexttemplate": "grantlee",
    "ktoblzcheck": "ktoblzcheck",
    "kubectl": "kubernetes-cli",
    "kubectl-ai": "kubectl-ai",
    "kyotocabinet": "kyoto-cabinet",
    "ladspa": "ladspa-sdk",
    "lager": "lager",
    "lame": "lame",
    "lapack": "lapack",
    "laszip": "laszip",
    "latex2html": "latex2html",
    "lazydocker": "lazydocker",
    "lazygit": "lazygit",
    "lcdproc": "lcdproc",
    "lcms": "little-cms2",
    "lcms2": "little-cms2",
    "lcov": "lcov",
    "lensfun": "lensfun",
    "leptonlib": "leptonica",
    "less": "less",
    "lesspipe": "lesspipe",
    "lexbor": "lexbor",
    "lftp": "lftp",
    "lgeneral": "lgeneral",
    "libaac": "fdk-aac",
    "libaacs": "libaacs",
    "libadwaita": "libadwaita",
    "libaec": "libaec",
    "libaio": "libaio",
    "libantlr3c": "libantlr3c",
    "libao": "libao",
    "libaom": "aom",
    "libarchive": "libarchive",
    "libass": "libass",
    "libassuan": "libassuan",
    "libatomic_ops": "libatomic_ops",
    "libavif": "libavif",
    "libbdplus": "libbdplus",
    "libbluray": "libbluray",
    "libbpf": "libbpf",
    "libbs2b": "libbs2b",
    "libbsd": "libbsd",
    "libcaca": "libcaca",
    "libcanberra": "libcanberra",
    "libcap": "libcap",
    "libcap-ng": "libcap-ng",
    "libcbor": "libcbor",
    "libcddb": "libcddb",
    "libcdio": "libcdio",
    "libcdio-paranoia": "libcdio-paranoia",
    "libcdr": "libcdr",
    "libchewing": "libchewing",
    "libclc": "libclc",
    "libcoap": "libcoap",
    "libconfig": "libconfig",
    "libconfuse": "confuse",
    "libcotp": "libcotp",
    "libcpptest": "cpptest",
    "libcpuid": "libcpuid",
    "libcroco": "libcroco",
    "libcss": "libcss",
    "libcue": "libcue",
    "libcxx": "clang-format",
    "libcxxabi": "clang-format",
    "libcyaml": "libcyaml",
    "libdaemon": "libdaemon",
    "libdap": "libdap",
    "libdatrie": "libdatrie",
    "libdazzle": "libdazzle",
    "libdbi": "libdbi",
    "libdbusmenu": "libdbusmenu",
    "libdc1394": "libdc1394",
    "libde265": "libde265",
    "libdecor": "libdecor",
    "libdeflate": "libdeflate",
    "libdex": "libdex",
    "libdiscid": "libdiscid",
    "libdmx": "libdmx",
    "libdnet": "libdnet",
    "libdrm": "libdrm",
    "libdsk": "libdsk",
    "libdv": "libdv",
    "libdvbcsa": "libdvbcsa",
    "libdvbpsi": "libdvbpsi",
    "libdvdcss": "libdvdcss",
    "libdvdnav": "libdvdnav",
    "libdvdread": "libdvdread",
    "libeatmydata": "libeatmydata",
    "libebml": "libebml",
    "libebur128": "libebur128",
    "libedit": "libedit",
    "libelf": "elfutils",
    "libemf2svg": "libemf2svg",
    "libestr": "libestr",
    "libetpan": "libetpan",
    "libev": "libev",
    "libevdev": "libevdev",
    "libevent": "libevent",
    "libewf": "libewf",
    "libexif": "libexif",
    "libexosip2": "libexosip",
    "libextractor": "libextractor",
    "libfastjson": "libfastjson",
    "libffi": "libffi",
    "libfido2": "libfido2",
    "libfishsound": "libfishsound",
    "libfoma": "foma",
    "libfontenc": "libfontenc",
    "libfreehand": "libfreehand",
    "libfs": "libfs",
    "libftdi": "libftdi",
    "libftdi1": "libftdi",
    "libfyaml": "libfyaml",
    "libgadu": "libgadu",
    "libgcrypt": "libgcrypt",
    "libgd": "gd",
    "libgda": "libgda",
    "libgdata": "libgdata",
    "libgdiplus": "mono-libgdiplus",
    "libgedit-amtk": "libgedit-amtk",
    "libgedit-gfls": "libgedit-gfls",
    "libgedit-gtksourceview": "libgedit-gtksourceview",
    "libgedit-tepl": "libgedit-tepl",
    "libgee": "libgee",
    "libgeotiff": "libgeotiff",
    "libghthash": "libghthash",
    "libgif": "giflib",
    "libgit2": "libgit2",
    "libgme": "game-music-emu",
    "libgpg-error": "libgpg-error",
    "libgphoto": "libgphoto2",
    "libgsasl": "gsasl",
    "libgsf": "libgsf",
    "libgtop": "libgtop",
    "libgusb": "libgusb",
    "libgweather": "libgweather",
    "libgxps": "libgxps",
    "libhandy": "libhandy",
    "libharu": "libharu",
    "libhdhomerun": "libhdhomerun",
    "libheif": "libheif",
    "libical": "libical",
    "libice": "libice",
    "libicns": "libicns",
    "libiconv": "libiconv",
    "libid3tag": "libid3tag",
    "libidl": "libidl",
    "libidn": "libidn",
    "libidn2": "libidn2",
    "libigloo": "libigloo",
    "libimobiledevice": "libimobiledevice",
    "libimobiledevice-glue": "libimobiledevice-glue",
    "libiptcdata": "libiptcdata",
    "libirecovery": "libirecovery",
    "libiscsi": "libiscsi",
    "libisofs": "libisofs",
    "libjcat": "libjcat",
    "libjpeg": "jpeg",
    "libjpeg-turbo": "jpeg-turbo",
    "libjwt": "libjwt",
    "libjxl": "jpeg-xl",
    "libkeyfinder": "libkeyfinder",
    "libks": "libks",
    "libksba": "libksba",
    "liblc3": "liblc3",
    "liblcf": "liblcf",
    "liblo": "liblo",
    "liblockfile": "liblockfile",
    "liblouis": "liblouis",
    "libltc": "libltc",
    "liblzf": "liblzf",
    "libmaa": "libmaa",
    "libmad": "mad",
    "libmatroska": "libmatroska",
    "libmaxminddb": "libmaxminddb",
    "libmd": "libmd",
    "libmemcached": "libmemcached",
    "libmhash": "mhash",
    "libmicrohttpd": "libmicrohttpd",
    "libmikmod": "libmikmod",
    "libmms": "libmms",
    "libmng": "libmng",
    "libmnl": "libmnl",
    "libmodbus": "libmodbus",
    "libmodplug": "libmodplug",
    "libmowgli": "libmowgli",
    "libmp3splt": "libmp3splt",
    "libmpcdec": "musepack",
    "libmpd": "libmpd",
    "libmpdclient": "libmpdclient",
    "libmpeg2": "libmpeg2",
    "libmrss": "libmrss",
    "libmspub": "libmspub",
    "libmtp": "libmtp",
    "libmusicbrainz": "libmusicbrainz",
    "libmypaint": "libmypaint",
    "libnet": "libnet",
    "libnfnetlink": "libnfnetlink",
    "libnfs": "libnfs",
    "libnftnl": "libnftnl",
    "libnice": "libnice",
    "libnids": "libnids",
    "libnl": "libnl",
    "libnotify": "libnotify",
    "libnpupnp": "libnpupnp",
    "libnsl": "libnsl",
    "libnxml": "libnxml",
    "libofx": "libofx",
    "libogg": "libogg",
    "liboggz": "oggz",
    "liboil": "liboil",
    "liboping": "liboping",
    "libopus": "opus",
    "libopusenc": "libopusenc",
    "libosinfo": "libosinfo",
    "libosip": "libosip",
    "libosip2": "libosip",
    "libotr": "libotr",
    "libowfat": "libowfat",
    "libp11": "libp11",
    "libpanel": "libpanel",
    "libpano": "libpano",
    "libpaper": "libpaper",
    "libpcap": "libpcap",
    "libpciaccess": "libpciaccess",
    "libpeas": "libpeas",
    "libpeas1": "libpeas",
    "libpg_query": "libpg_query",
    "libphonenumber": "libphonenumber",
    "libpinyin": "libpinyin",
    "libpipeline": "libpipeline",
    "libplacebo": "libplacebo",
    "libplist": "libplist",
    "libpng": "libpng",
    "libprelude": "libprelude",
    "libproxy": "libproxy",
    "libpsl": "libpsl",
    "libpthread-stubs": "libpthread-stubs",
    "libptytty": "libptytty",
    "libqalculate": "libqalculate",
    "libqrencode": "qrencode",
    "libquicktime": "libquicktime",
    "libraw": "libraw",
    "libressl": "libressl",
    "librest": "librest",
    "libretls": "libretls",
    "librevenge": "librevenge",
    "librist": "librist",
    "librsvg": "librsvg",
    "librsync": "librsync",
    "librtlsdr": "librtlsdr",
    "libsamplerate": "libsamplerate",
    "libsass": "libsass",
    "libsdl2": "sdl2",
    "libsdl2_gfx": "sdl2_gfx",
    "libsdl2_image": "sdl2_image",
    "libsdl2_mixer": "sdl2_mixer",
    "libsdl2_ttf": "sdl2_ttf",
    "libsdl3": "sdl3",
    "libsdl3_image": "sdl3_image",
    "libsdl3_ttf": "sdl3_ttf",
    "libsdl_gfx": "sdl_gfx",
    "libseccomp": "libseccomp",
    "libsecret": "libsecret",
    "libselinux": "libselinux",
    "libsepol": "libsepol",
    "libserialport": "libserialport",
    "libshout": "libshout",
    "libshumate": "libshumate",
    "libsigc++": "libsigc++",
    "libsigc++1": "libsigc++",
    "libsigc++12": "libsigc++",
    "libsigc++2": "libsigc++",
    "libsignal-protocol-c": "libsignal-protocol-c",
    "libsigrok": "libsigrok",
    "libsigrokdecode": "libsigrokdecode",
    "libsigsegv": "libsigsegv",
    "libsixel": "libsixel",
    "libslirp": "libslirp",
    "libsm": "libsm",
    "libsmi": "libsmi",
    "libsndfile": "libsndfile",
    "libsodium": "libsodium",
    "libsoundio": "libsoundio",
    "libsoup": "libsoup",
    "libsoup3": "libsoup",
    "libspatialindex": "spatialindex",
    "libspectre": "libspectre",
    "libspiro": "libspiro",
    "libspnav": "libspnav",
    "libspng": "libspng",
    "libsrt": "srt",
    "libssh": "libssh",
    "libssh2": "libssh2",
    "libstatgrab": "libstatgrab",
    "libstemmer": "snowball",
    "libstrophe": "libstrophe",
    "libsvg": "libsvg",
    "libsvg-cairo": "libsvg-cairo",
    "libtar": "libtar",
    "libtasn1": "libtasn1",
    "libtatsu": "libtatsu",
    "libthai": "libthai",
    "libtheora": "theora",
    "libtiff": "libtiff",
    "libtins": "libtins",
    "libtirpc": "libtirpc",
    "libtomcrypt": "libtomcrypt",
    "libtommath": "libtommath",
    "libtool": "libtool",
    "libtorrent": "libtorrent-rakshasa",
    "libtpms": "libtpms",
    "libudfread": "libudfread",
    "libuecc": "libuecc",
    "libultrahdr": "libultrahdr",
    "libunibreak": "libunibreak",
    "libunicode": "libunicode",
    "libuninameslist": "libuninameslist",
    "libunistring": "libunistring",
    "libunwind": "clang-format",
    "libupnp": "libupnp",
    "libupnpp": "libupnpp",
    "liburcu": "userspace-rcu",
    "liburing": "liburing",
    "libusb": "libusb",
    "libusb-compat": "libusb-compat",
    "libusbmuxd": "libusbmuxd",
    "libusrsctp": "libusrsctp",
    "libuv": "libuv",
    "libva": "libva",
    "libvdpau": "libvdpau",
    "libvirt": "libvirt",
    "libvirt-glib": "libvirt-glib",
    "libvirt-python": "libvirt-python",
    "libvncserver": "libvncserver",
    "libvolk": "volk",
    "libvorbis": "libvorbis",
    "libvpx": "libvpx",
    "libwebp": "webp",
    "libwebsockets": "libwebsockets",
    "libwmf": "libwmf",
    "libwpd": "libwpd",
    "libwpe": "libwpe",
    "libx11": "libx11",
    "libxau": "libxau",
    "libxaw": "libxaw",
    "libxcb": "libxcb",
    "libxcomposite": "libxcomposite",
    "libxcrypt": "libxcrypt",
    "libxcursor": "libxcursor",
    "libxcvt": "libxcvt",
    "libxdamage": "libxdamage",
    "libxdg-basedir": "libxdg-basedir",
    "libxdmcp": "libxdmcp",
    "libxext": "libxext",
    "libxfixes": "libxfixes",
    "libxfont": "libxfont",
    "libxfont2": "libxfont2",
    "libxft": "libxft",
    "libxi": "libxi",
    "libxinerama": "libxinerama",
    "libxkbfile": "libxkbfile",
    "libxmi": "libxmi",
    "libxml": "libxml2",
    "libxml++": "libxml++",
    "libxml1": "libxml2",
    "libxmlb": "libxmlb",
    "libxmp": "libxmp",
    "libxmu": "libxmu",
    "libxo": "libxo",
    "libxp": "libxp",
    "libxpm": "libxpm",
    "libxpresent": "libxpresent",
    "libxrandr": "libxrandr",
    "libxrender": "libxrender",
    "libxres": "libxres",
    "libxscrnsaver": "libxscrnsaver",
    "libxshmfence": "libxshmfence",
    "libxslt": "libxslt",
    "libxspf": "libxspf",
    "libxt": "libxt",
    "libxtst": "libxtst",
    "libxv": "libxv",
    "libxvmc": "libxvmc",
    "libxxf86dga": "libxxf86dga",
    "libxxf86vm": "libxxf86vm",
    "libyaml": "libyaml",
    "libzdb": "libzdb",
    "libzim": "libzim",
    "libzip": "libzip",
    "libzmq": "zeromq",
    "libzvbi": "zvbi",
    "lief": "lief",
    "lightning": "lightning",
    "lighttpd": "lighttpd",
    "lilv": "lilv",
    "lima": "lima",
    "limine": "limine",
    "link-grammar": "link-grammar",
    "links": "links",
    "linux": "linux-headers@4.4",
    "linux-header": "linux-headers@4.4",
    "liquid-dsp": "liquid-dsp",
    "liquidctl": "liquidctl",
    "live": "openrtsp",
    "llama-cpp": "llama.cpp",
    "lld": "clang-format",
    "lldb": "clang-format",
    "llvm": "clang-format",
    "lm_sensors": "lm-sensors",
    "lmdb": "lmdb",
    "log4c": "log4c",
    "log4cplus": "log4cplus",
    "log4cpp": "log4cpp",
    "log4cxx": "log4cxx",
    "logcheck": "logcheck",
    "logrotate": "logrotate",
    "loudmouth": "loudmouth",
    "lpeg": "lpeg",
    "lrzsz": "lrzsz",
    "lsdvd": "lsdvd",
    "lsof": "lsof",
    "lttng-ust": "lttng-ust",
    "lua": "lua",
    "luajit": "luajit",
    "luarocks": "luarocks",
    "lutok": "lutok",
    "lux": "lux",
    "lv2": "lv2",
    "lvm2": "device-mapper",
    "lxsplit": "lxsplit",
    "lynx": "lynx",
    "lz4": "lz4",
    "lzip": "lzip",
    "lziprecover": "lziprecover",
    "lzo": "lzo",
    "lzop": "lzop",
    "lzsa": "lzsa",
    "m4": "m4",
    "macchanger": "macchanger",
    "macchina": "macchina",
    "madplay": "madplay",
    "make": "make",
    "makedepend": "makedepend",
    "makeself": "makeself",
    "mame": "mame",
    "man": "man-db",
    "mapnik": "mapnik",
    "mariadb": "mariadb",
    "mariadb-connector-c": "mariadb-connector-c",
    "markdown": "python-markdown",
    "masscan": "masscan",
    "matplotlib": "python-matplotlib",
    "matterbridge": "matterbridge",
    "maven": "maven",
    "maven1": "maven",
    "mawk": "mawk",
    "maxima": "maxima",
    "mbedtls": "mbedtls",
    "mc": "midnight-commander",
    "mcabber": "mcabber",
    "mcp-toolbox": "mcp-toolbox",
    "md4c": "md4c",
    "mda-lv2": "mda-lv2",
    "mdbtools": "mdbtools",
    "mdds": "mdds",
    "mdf2iso": "mdf2iso",
    "mednafen": "mednafen",
    "megatools": "megatools",
    "memcached": "memcached",
    "memtester": "memtester",
    "menhir": "menhir",
    "mercurial": "mercurial",
    "mercury": "mercury",
    "mesa": "mesa",
    "mesa-legacy": "mesa",
    "meson": "meson",
    "mgba": "mgba",
    "micro": "micro",
    "micropython": "micropython",
    "mikmod": "mikmod",
    "mimalloc": "mimalloc",
    "minicom": "minicom",
    "minikube": "minikube",
    "minio": "minio",
    "minipro": "minipro",
    "minised": "minised",
    "minisign": "minisign",
    "miniupnpc": "miniupnpc",
    "minizip-ng": "minizip-ng",
    "mjpegtools": "mjpegtools",
    "mkcert": "mkcert",
    "mkfontscale": "mkfontscale",
    "mksh": "mksh",
    "mlt": "mlt",
    "mm-common": "mm-common",
    "mmv": "mmv",
    "moarvm": "moarvm",
    "mod_security": "modsecurity",
    "mods": "mods",
    "moe": "moe",
    "mold": "mold",
    "monetdb": "monetdb",
    "mongo-c-driver": "mongo-c-driver",
    "monit": "monit",
    "monitoring-plugins": "monitoring-plugins",
    "monkeysphere": "monkeysphere",
    "mono": "mono",
    "monolith": "monolith",
    "moon-buggy": "moon-buggy",
    "moreutils": "moreutils",
    "mosh": "mosh",
    "mosquitto": "mosquitto",
    "most": "most",
    "motif": "openmotif",
    "mozjs": "spidermonkey",
    "mp3info": "mp3info",
    "mp3splt": "mp3splt",
    "mpc": "libmpc",
    "mpcli": "mpc",
    "mpd": "mpd",
    "mpfr": "mpfr",
    "mpg123": "mpg123",
    "mpg321": "mpg321",
    "mpgtx": "mpgtx",
    "mpich": "mpich",
    "mplayer": "mplayer",
    "mpop": "mpop",
    "mpv": "mpv",
    "mrtg": "mrtg",
    "msedit": "msedit",
    "msgpack-cxx": "msgpack-cxx",
    "msgpuck": "msgpuck",
    "msitools": "msitools",
    "msmtp": "msmtp",
    "mtools": "mtools",
    "mtr": "mtr",
    "mujs": "mujs",
    "multitail": "multitail",
    "muon": "muon",
    "muparser": "muparser",
    "mupdf": "mupdf",
    "mupen64plus": "mupen64plus",
    "mutt": "mutt",
    "mxml": "libmxml",
    "myman": "myman",
    "mypaint-brushes": "mypaint-brushes",
    "myrepos": "mr",
    "mysql": "mysql",
    "mysql++": "mysql++",
    "nagios": "nagios",
    "nagios-plugins": "nagios-plugins",
    "nano": "nano",
    "nanomsg": "nanomsg",
    "nasm": "nasm",
    "ncc": "ncc",
    "ncdu": "ncdu",
    "ncftp": "ncftp",
    "ncmpc": "ncmpc",
    "ncmpcpp": "ncmpcpp",
    "ncompress": "ncompress",
    "ncurses": "ncurses",
    "ne": "ne",
    "neatvi": "neatvi",
    "nedit": "nedit",
    "nemu": "nemu",
    "neofetch": "neofetch",
    "neon": "neon",
    "neovim": "neovim",
    "net-snmp": "net-snmp",
    "net-tools": "net-tools",
    "netcat": "netcat",
    "netcdf": "netcdf",
    "nethack": "nethack",
    "nethogs": "nethogs",
    "netpbm": "netpbm",
    "nettle": "nettle",
    "neverlang": "never",
    "newsboat": "newsboat",
    "newt": "newt",
    "nftables": "nftables",
    "nghttp2": "libnghttp2",
    "nghttp3": "libnghttp3",
    "nginx": "nginx",
    "ngircd": "ngircd",
    "ngrep": "ngrep",
    "ngspice": "libngspice",
    "nicotine-plus": "nicotine-plus",
    "nim": "nim",
    "ninja": "ninja",
    "nip4": "nip4",
    "nload": "nload",
    "nlohmann-json": "nlohmann-json",
    "nlopt": "nlopt",
    "nmap": "nmap",
    "nmh": "nmh",
    "nng": "nng",
    "nodejs": "node",
    "normalize": "normalize",
    "notcurses": "notcurses",
    "npth": "npth",
    "nqp": "nqp",
    "nrg2iso": "nrg2iso",
    "nsd": "nsd",
    "nspr": "nspr",
    "nss": "nss",
    "ntfs-3g": "ntfs-3g",
    "ntfsprogs": "ntfs-3g",
    "ntp": "ntp",
    "numactl": "numactl",
    "numbat": "numbat",
    "numpy": "numpy",
    "nushell": "nushell",
    "nuspell": "nuspell",
    "nut": "nut",
    "nvi": "nvi",
    "nyx": "nyx",
    "nzbget": "nzbget",
    "oath-toolkit": "oath-toolkit",
    "ocaml": "ocaml",
    "ocaml-findlib": "ocaml-findlib",
    "ocrad": "ocrad",
    "ocrmypdf": "ocrmypdf",
    "octave": "octave",
    "odin": "odin",
    "ogmtools": "ogmtools",
    "oh-my-posh": "oh-my-posh",
    "oils-for-unix": "oils-for-unix",
    "oksh": "oksh",
    "olm": "libolm",
    "onig": "oniguruma",
    "onnxruntime": "onnxruntime",
    "openal": "openal-soft",
    "openblas": "openblas",
    "opencascade": "opencascade",
    "opencl-clhpp": "opencl-clhpp-headers",
    "opencl-headers": "opencl-headers",
    "opencolorio": "opencolorio",
    "openconnect": "openconnect",
    "opencore-amr": "opencore-amr",
    "opencv": "opencv",
    "opendbx": "opendbx",
    "openexr": "openexr",
    "openfpgaloader": "openfpgaloader",
    "openfst": "openfst",
    "openh264": "openh264",
    "openimageio": "openimageio",
    "openjdk": "openjdk",
    "openjpeg": "openjpeg",
    "openjph": "openjph",
    "openldap": "openldap",
    "openlibm": "openlibm",
    "openmotif": "openmotif",
    "openmp": "clang-format",
    "openocd": "open-ocd",
    "opensc": "opensc",
    "openscenegraph": "open-scene-graph",
    "openslide": "openslide",
    "openslp": "openslp",
    "openssh": "openssh",
    "openssl": "openssl@3",
    "opentofu": "opentofu",
    "openvdb": "openvdb",
    "openvino": "openvino",
    "openvpn": "openvpn",
    "opus-tools": "opus-tools",
    "opusfile": "opusfile",
    "or-tools": "or-tools",
    "orc": "orc",
    "otf2bdf": "otf2bdf",
    "ouch": "ouch",
    "ox": "ox",
    "p0f": "p0f",
    "p11-kit": "p11-kit",
    "pam": "linux-pam",
    "pam-u2f": "pam-u2f",
    "pan": "pan",
    "pango": "pango",
    "pangomm": "pangomm",
    "pangomm1": "pangomm",
    "paperkey": "paperkey",
    "papers": "gnome-papers",
    "papilo": "papilo",
    "par2cmdline": "par2",
    "parallel": "parallel",
    "parqeye": "parqeye",
    "parrot": "parrot",
    "pass": "pass",
    "pass-git-helper": "pass-git-helper",
    "pass-otp": "pass-otp",
    "patch": "gpatch",
    "patchelf": "patchelf",
    "patchutils": "patchutils",
    "pcb": "pcb",
    "pciutils": "pciutils",
    "pcre": "pcre",
    "pcre2": "pcre2",
    "pcsc-lite": "pcsc-lite",
    "pdftilecut": "pdftilecut",
    "pdftk": "pdftk-java",
    "pdnsd": "pdnsd",
    "perceptualdiff": "perceptualdiff",
    "perf": "linux-headers@4.4",
    "perl": "perl",
    "perltidy": "perltidy",
    "pet": "pet",
    "pfetch": "pfetch",
    "pgbouncer": "pgbouncer",
    "phodav": "phodav",
    "php": "php",
    "physfs": "physfs",
    "pidgin": "pidgin",
    "pigz": "pigz",
    "pike": "pike",
    "piknik": "piknik",
    "pillow": "pillow",
    "pinentry": "pinentry",
    "pinfo": "pinfo",
    "pipewire": "pipewire",
    "pipx": "pipx",
    "pixie": "pixie",
    "pixman": "pixman",
    "plotutils": "plotutils",
    "plplot": "plplot",
    "plutovg": "plutovg",
    "pmccabe": "pmccabe",
    "pngnq": "pngnq",
    "po4a": "po4a",
    "pocl": "pocl",
    "poco": "poco",
    "podman": "podman",
    "podofo": "podofo",
    "poetry": "poetry",
    "poke": "poke",
    "polkit": "polkit",
    "polyglot": "polyglot",
    "polyml": "polyml",
    "poppler": "poppler",
    "popt": "popt",
    "portaudio": "portaudio",
    "portmidi": "portmidi",
    "postgresql": "libpq",
    "potrace": "potrace",
    "povray": "povray",
    "ppl": "ppl",
    "pqiv": "pqiv",
    "pre-commit": "pre-commit",
    "primecount": "primecount",
    "privoxy": "privoxy",
    "prjtrellis": "prjtrellis",
    "procmail": "procmail",
    "procps": "procps",
    "proftpd": "proftpd",
    "proj": "proj",
    "prometheus": "prometheus",
    "protobuf": "protobuf",
    "protobuf-c": "protobuf-c",
    "protozero": "protozero",
    "psftools": "psftools",
    "pspg": "pspg",
    "pssh": "pssh",
    "pstoedit": "pstoedit",
    "ptex": "ptex",
    "pugixml": "pugixml",
    "pulseaudio": "pulseaudio",
    "pure-ftpd": "pure-ftpd",
    "putty": "putty",
    "pv": "pv",
    "pwgen": "pwgen",
    "pybind": "pybind11",
    "pycairo": "py3cairo",
    "pycparser": "pycparser",
    "pydantic": "pydantic",
    "pyenv": "pyenv",
    "pygments": "pygments",
    "pygobject": "pygobject3",
    "pymupdf": "pymupdf",
    "pyqt": "pyqt",
    "pyqt-builder": "pyqt-builder",
    "pystring": "pystring",
    "python": "python@3.10",
    "python-build": "python-build",
    "python-lsp-server": "python-lsp-server",
    "python-maturin": "maturin",
    "python-tabulate": "python-tabulate",
    "python-virtualenv": "virtualenv",
    "python2": "python@3.10",
    "pytorch": "pytorch",
    "qalculate-gtk": "qalculate-gtk",
    "qbe": "qbe",
    "qca2": "qca",
    "qca2-cyrus-sasl": "qca",
    "qca2-ossl": "qca",
    "qemu": "qemu",
    "qhull": "qhull",
    "qjackctl": "qjackctl",
    "qjson": "qjson",
    "qpdf": "qpdf",
    "qt-qca": "qca",
    "qt-qca-sasl": "qca",
    "qt3": "qt",
    "qt4": "qt",
    "qt65compat": "qt",
    "qtkeychain": "qtkeychain",
    "quazip": "quazip",
    "quickjs": "quickjs",
    "quilt": "quilt",
    "quotatool": "quotatool",
    "r": "r",
    "rabbitmq-c": "rabbitmq-c",
    "racket": "minimal-racket",
    "radare2": "radare2",
    "radvd": "radvd",
    "ragel": "ragel",
    "rakudo": "rakudo",
    "rancid": "rancid",
    "ranger": "ranger",
    "rapidjson": "rapidjson",
    "rapidyaml": "rapidyaml",
    "rarian": "rarian",
    "rasqal": "rasqal",
    "rav1e": "rav1e",
    "raylib": "raylib",
    "rc": "rc",
    "rclone": "rclone",
    "rcm": "rcm",
    "rcs": "rcs",
    "rdate": "rdate",
    "rdfind": "rdfind",
    "re2": "re2",
    "re2c": "re2c",
    "readline": "readline",
    "readosm": "readosm",
    "recode": "recode",
    "recoverjpeg": "recoverjpeg",
    "recutils": "recutils",
    "redis": "redis",
    "redland": "redland",
    "redshift": "redshift",
    "remind": "remind",
    "repo": "repo",
    "reproc": "reproc",
    "rest": "librest",
    "rhash": "rhash",
    "rio": "rio-terminal",
    "ripgrep": "ripgrep",
    "ripmime": "ripmime",
    "rlog": "rlog",
    "robin-map": "robin-map",
    "rocq": "rocq",
    "root": "root",
    "rpcsvc-proto": "rpcsvc-proto",
    "rpki-client": "rpki-client",
    "rpm": "rpm",
    "rrdtool": "rrdtool",
    "rsnapshot": "rsnapshot",
    "rsync": "rsync",
    "rsyslog": "rsyslog",
    "rtl_433": "rtl_433",
    "rtmidi": "rtmidi",
    "rtmpdump": "rtmpdump",
    "rtorrent": "rtorrent",
    "rubberband": "rubberband",
    "ruby": "ruby",
    "runc": "runc",
    "runit": "runit",
    "rust-analyzer": "rust-analyzer",
    "rust-src": "rust",
    "rustc": "rust",
    "rustscan": "rustscan",
    "rxvt-unicode": "rxvt-unicode",
    "ry": "ry",
    "rzip": "rzip",
    "s-nail": "s-nail",
    "s2geometry": "s2geometry",
    "s3cmd": "s3cmd",
    "s3fs-fuse": "s3fs",
    "sad": "sad",
    "samba": "samba",
    "sane-backends": "sane-backends",
    "sassc": "sassc",
    "sblim-sfcc": "sblim-sfcc",
    "sbt": "sbt",
    "scala": "scala",
    "scale2x": "scale2x",
    "sccache": "sccache",
    "scdoc": "scdoc",
    "schroedinger": "schroedinger",
    "scip-solver": "scip",
    "scons": "scons",
    "screen": "screen",
    "scrypt": "scrypt",
    "scummvm": "scummvm",
    "sdcc": "sdcc",
    "sdl12-compat": "sdl12-compat",
    "sed": "gnu-sed",
    "sentencepiece": "sentencepiece",
    "ser2net": "ser2net",
    "serd": "serd",
    "serf": "apache-serf",
    "setconf": "setconf",
    "shaderc": "shaderc",
    "shared-mime-info": "shared-mime-info",
    "shntool": "shntool",
    "sigrok-cli": "sigrok-cli",
    "simde": "simde",
    "simdjson": "simdjson",
    "simdutf": "simdutf",
    "simple-scan": "simple-scan",
    "simutrans": "simutrans",
    "sip": "sip",
    "sipcalc": "sipcalc",
    "sipp": "sipp",
    "sipsak": "sipsak",
    "six": "six",
    "skalibs": "skalibs",
    "skopeo": "skopeo",
    "slang": "s-lang",
    "sloccount": "sloccount",
    "slrn": "slrn",
    "slurm": "slurm",
    "smalltalk": "gnu-smalltalk",
    "smartmontools": "smartmontools",
    "smartypants": "smartypants",
    "smenu": "smenu",
    "smpeg": "smpeg2",
    "snappy": "snappy",
    "snapraid": "snapraid",
    "sniffglue": "sniffglue",
    "sniffnet": "sniffnet",
    "snort": "snort",
    "snowballstemmer": "snowball",
    "snownews": "snownews",
    "soapysdr": "soapysdr",
    "socat": "socat",
    "soft-serve": "soft-serve",
    "softhsm": "softhsm",
    "soplex": "soplex",
    "sord": "sord",
    "soundtouch": "sound-touch",
    "sox": "sox",
    "soxr": "libsoxr",
    "spandsp": "spandsp",
    "sparkey": "sparkey",
    "sparse": "sparse",
    "sparsehash": "google-sparsehash",
    "spawn-fcgi": "spawn-fcgi",
    "spdlog": "spdlog",
    "speex": "speex",
    "speexdsp": "speexdsp",
    "spglib": "spglib",
    "sphinx-doc": "sphinx-doc",
    "spice-gtk": "spice-gtk",
    "spice-protocol": "spice-protocol",
    "spirv-cross": "spirv-cross",
    "spirv-headers": "spirv-headers",
    "spirv-llvm-translator": "spirv-llvm-translator",
    "spirv-tools": "spirv-tools",
    "splint": "splint",
    "sqlcipher": "sqlcipher",
    "sqlite": "sqlite",
    "sqlite2": "sqlite",
    "sqlmap": "sqlmap",
    "squashfs-tools": "squashfs",
    "squashfuse": "squashfuse",
    "squid": "squid",
    "sratom": "sratom",
    "srecord": "srecord",
    "ssh-audit": "ssh-audit",
    "sshfs": "sshfs",
    "sshguard": "sshguard",
    "sshpass": "sshpass",
    "sslh": "sslh",
    "ssss": "ssss",
    "starship": "starship",
    "startup-notification": "startup-notification",
    "stella": "stella",
    "stern": "stern",
    "stgit": "stgit",
    "stm32flash": "stm32flash",
    "stockfish": "stockfish",
    "stow": "stow",
    "strace": "strace",
    "streamripper": "streamripper",
    "stress": "stress",
    "stress-ng": "stress-ng",
    "strongswan": "strongswan",
    "stunnel": "stunnel",
    "subversion": "subversion",
    "suil": "suil",
    "superfile": "superfile",
    "supertux": "supertux",
    "supervisor": "supervisor",
    "surfer": "surfer",
    "surfraw": "surfraw",
    "suricata": "suricata",
    "svt-av1": "svt-av1",
    "svt-vp9": "svt-vp9",
    "swftools": "swftools",
    "swi-prolog": "swi-prolog",
    "swift": "swift",
    "swig": "swig",
    "sword": "sword",
    "swtpm": "swtpm",
    "sylpheed": "sylpheed",
    "syncthing": "syncthing",
    "synergy": "synergy-core",
    "sysbench": "sysbench",
    "syslog-ng": "syslog-ng",
    "sysprof": "sysprof",
    "sysstat": "sysstat",
    "systemc": "systemc",
    "systemd": "systemd",
    "t1lib": "t1lib",
    "tabulate": "tabulate",
    "taglib": "taglib",
    "tailscale": "tailscale",
    "talloc": "talloc",
    "tar": "gnu-tar",
    "task": "task",
    "taskd": "taskd",
    "tasksh": "tasksh",
    "tbb": "tbb",
    "tcc": "tcc",
    "tclap": "tclap",
    "tcpdump": "tcpdump",
    "tcpflow": "tcpflow",
    "tcpreplay": "tcpreplay",
    "tcptrace": "tcptrace",
    "tcptraceroute": "tcptraceroute",
    "tcsh": "tcsh",
    "tdb": "tdb",
    "telegraf": "telegraf",
    "termcolor": "termcolor",
    "terraform": "terraform",
    "terraform-ls": "terraform-ls",
    "tesseract": "tesseract",
    "testdisk": "testdisk",
    "texi2html": "texi2html",
    "texinfo": "texinfo",
    "texlive": "texlive",
    "thefuck": "thefuck",
    "threadweaver": "threadweaver",
    "tidy": "tidy-html5",
    "tiff2png": "tiff2png",
    "tig": "tig",
    "tigervnc": "tiger-vnc",
    "time": "gnu-time",
    "timew": "timewarrior",
    "timidity++": "timidity",
    "tinyproxy": "tinyproxy",
    "tinysparql": "tinysparql",
    "tinyxml2": "tinyxml",
    "tio": "tio",
    "tkdiff": "tkdiff",
    "tllist": "tllist",
    "tlrc": "tlrc",
    "tmux": "tmux",
    "tnef": "tnef",
    "toilet": "toilet",
    "tomcat": "tomcat",
    "tomlplusplus": "tomlplusplus",
    "toot": "toot",
    "topgit": "topgit",
    "tor": "tor",
    "transmission": "transmission-cli",
    "trash-cli": "trash-cli",
    "tre": "tre",
    "tree": "tree",
    "tree-sitter": "tree-sitter",
    "trufflehog": "trufflehog",
    "ts": "task-spooler",
    "twm": "twm",
    "twolame": "two-lame",
    "txr": "txr",
    "txt2man": "txt2man",
    "txt2tags": "txt2tags",
    "typescript": "typescript",
    "typespeed": "typespeed",
    "typst": "typst",
    "tzdata": "tzdb",
    "u-boot": "u-boot-tools",
    "uchardet": "uchardet",
    "ucl": "ucl",
    "ucommon": "ucommon",
    "ucspi-tcp": "ucspi-tcp",
    "udis86": "udis86",
    "ugrep": "ugrep",
    "uhubctl": "uhubctl",
    "umkalang": "umka-lang",
    "umoci": "umoci",
    "umockdev": "umockdev",
    "unbound": "unbound",
    "uncrustify": "uncrustify",
    "uni2ascii": "uni2ascii",
    "unicorn": "unicorn",
    "unifdef": "unifdef",
    "unison": "unison",
    "units": "gnu-units",
    "unixodbc": "unixodbc",
    "unpaper": "unpaper",
    "unshield": "unshield",
    "unwind": "libunwind",
    "unzip": "unzip",
    "upx": "upx",
    "uriparser": "uriparser",
    "urlscan": "urlscan",
    "urlview": "urlview",
    "usbredir": "usbredir",
    "usbutils": "usbutils",
    "utf8proc": "utf8proc",
    "utfcpp": "utf8cpp",
    "uthash": "uthash",
    "util-linux": "gnu-getopt",
    "uudeview": "uudeview",
    "uutils-coreutils": "uutils-coreutils",
    "vala": "vala",
    "valgrind": "valgrind",
    "valkey": "valkey",
    "vbindiff": "vbindiff",
    "vcdimager": "vcdimager",
    "verilator": "verilator",
    "verovio": "verovio",
    "vice": "vice",
    "vidstab": "libvidstab",
    "vifm": "vifm",
    "vim": "vim",
    "vips": "vips",
    "virt-manager": "virt-manager",
    "virtualenvwrapper": "virtualenvwrapper",
    "vit": "vit",
    "vlang": "vlang",
    "vnstat": "vnstat",
    "vo-aacenc": "libvo-aacenc",
    "vo-amrwbenc": "vo-amrwbenc",
    "volk": "vulkan-volk",
    "vorbis-tools": "vorbis-tools",
    "vorbisgain": "vorbisgain",
    "vpn-slice": "vpn-slice",
    "vsftpd": "vsftpd",
    "vte": "vte3",
    "vtk": "vtk",
    "vulkan-headers": "vulkan-headers",
    "vulkan-loader": "vulkan-loader",
    "vulkan-tools": "vulkan-tools",
    "vulkan-utility-libraries": "vulkan-utility-libraries",
    "vulkan-validation-layers": "vulkan-validationlayers",
    "w3m": "w3m",
    "wasi-libc": "wasi-libc",
    "wasi-libcxx": "clang-format",
    "wasmer": "wasmer",
    "wavpack": "wavpack",
    "wayland": "wayland",
    "wayland-protocols": "wayland-protocols",
    "wdiff": "wdiff",
    "webhook": "webhook",
    "webkit": "webkitgtk",
    "webkitgtk": "webkitgtk",
    "webkitgtk41": "webkitgtk",
    "west": "west",
    "wget": "wget",
    "whisper-cpp": "whisper-cpp",
    "whois": "whois",
    "wimlib": "wimlib",
    "winetricks": "winetricks",
    "wireguard-tools": "wireguard-tools",
    "wireshark": "wireshark",
    "witr": "witr",
    "wmctrl": "wmctrl",
    "woff2": "woff2",
    "wolfssl": "wolfssl",
    "wput": "wput",
    "wren": "wren",
    "wslay": "wslay",
    "wv": "wv",
    "wv2": "wv2",
    "wwwoffle": "wwwoffle",
    "wxmaxima": "wxmaxima",
    "wxpython": "wxpython",
    "wxpython24": "wxpython",
    "wxwidgets": "wxwidgets",
    "wxwidgets24": "wxwidgets",
    "x11vnc": "x11vnc",
    "x264": "x264",
    "x265": "x265",
    "xa": "xa",
    "xan": "xan",
    "xapian-core": "xapian",
    "xapian-omega": "omega",
    "xauth": "xauth",
    "xaw3d": "libxaw3d",
    "xbitmaps": "xbitmaps",
    "xboard": "xboard",
    "xbyak": "xbyak",
    "xcb-proto": "xcb-proto",
    "xcb-util": "xcb-util",
    "xcb-util-cursor": "xcb-util-cursor",
    "xcb-util-image": "xcb-util-image",
    "xcb-util-keysyms": "xcb-util-keysyms",
    "xcb-util-renderutil": "xcb-util-renderutil",
    "xcb-util-wm": "xcb-util-wm",
    "xclip": "xclip",
    "xdelta": "xdelta",
    "xdelta3": "xdelta",
    "xdotool": "xdotool",
    "xdpyinfo": "xdpyinfo",
    "xerces-c": "xerces-c",
    "xeyes": "xeyes",
    "xfig": "xfig",
    "xinit": "xinit",
    "xinput": "xinput",
    "xkbcommon": "libxkbcommon",
    "xkbcomp": "xkbcomp",
    "xkeyboard-config": "xkeyboard-config",
    "xlsclients": "xlsclients",
    "xml2rfc": "xml2rfc",
    "xmlrpc-c": "xmlrpc-c",
    "xmlsec": "libxmlsec1",
    "xmlstarlet": "xmlstarlet",
    "xmlto": "xmlto",
    "xmltoman": "xmltoman",
    "xmodmap": "xmodmap",
    "xmp": "xmp",
    "xonsh": "xonsh",
    "xorg-server": "xorg-server",
    "xorg-util-macros": "util-macros",
    "xorgproto": "xorgproto",
    "xpdf": "xpdf",
    "xplanet": "xplanet",
    "xprop": "xprop",
    "xrdb": "xrdb",
    "xsane": "xsane",
    "xsimd": "xsimd",
    "xterm": "xterm",
    "xtrans": "xtrans",
    "xvid": "xvid",
    "xwininfo": "xwininfo",
    "xxhash": "xxhash",
    "xz": "xz",
    "yajl": "yajl",
    "yaml-cpp": "yaml-cpp",
    "yamllint": "yamllint",
    "yara": "yara",
    "yash": "yash",
    "yasm": "yasm",
    "yazi": "yazi",
    "yelp-tools": "yelp-tools",
    "yle-dl": "yle-dl",
    "yosys": "yosys",
    "you-get": "you-get",
    "youtubedr": "youtubedr",
    "yq": "yq",
    "yt-dlp": "yt-dlp",
    "yubico-piv-tool": "yubico-piv-tool",
    "yubikey-manager": "ykman",
    "yyjson": "yyjson",
    "zabbix": "zabbix",
    "zarith": "ocaml-zarith",
    "zeek": "zeek",
    "zellij": "zellij",
    "zenity": "zenity",
    "zig": "zig",
    "zile": "zile",
    "zimg": "zimg",
    "zip": "zip",
    "zita-convolver": "zita-convolver",
    "zix": "zix",
    "zlib": "minizip",
    "zlib-ng": "zlib-ng",
    "zls": "zls",
    "znc": "znc",
    "zopfli": "zopfli",
    "zoxide": "zoxide",
    "zpaqfranz": "zpaqfranz",
    "zsh": "zsh",
    "zstd": "zstd",
    "zsync": "zsync",
    "zug": "zug",
    "zxing-cpp": "zxing-cpp",
    "zziplib": "libzzip"
  }
}